{
    "symbol": "KVYO",
    "annualReports": [
        {
            "fiscalDateEnding": "2023-12-31",
            "reportedCurrency": "USD",
            "grossProfit": "520211000",
            "totalRevenue": "698093000",
            "costOfRevenue": "788160000",
            "costofGoodsAndServicesSold": "177888000",
            "operatingIncome": "-330622000",
            "sellingGeneralAndAdministrative": "588656000",
            "researchAndDevelopment": "262177000",
            "operatingExpenses": "850833000",
            "investmentIncomeNet": "24051000",
            "netInterestIncome": "0",
            "interestIncome": "24051000",
            "interestExpense": "0",
            "nonInterestIncome": "698093000",
            "otherNonOperatingIncome": "-470000",
            "depreciation": "None",
            "depreciationAndAmortization": "13700000",
            "incomeBeforeTax": "-307041000",
            "incomeTaxExpense": "1192000",
            "interestAndDebtExpense": "0",
            "netIncomeFromContinuingOperations": "-308233000",
            "comprehensiveIncomeNetOfTax": "-308233000",
            "ebit": "-324412000",
            "ebitda": "-310761000",
            "netIncome": "-308233000"
        }
    ],
    "quarterlyReports": [
        {
            "fiscalDateEnding": "2023-12-31",
            "reportedCurrency": "USD",
            "grossProfit": "156605000",
            "totalRevenue": "201612000",
            "costOfRevenue": "189323000",
            "costofGoodsAndServicesSold": "45013000",
            "operatingIncome": "-36330000",
            "sellingGeneralAndAdministrative": "140300000",
            "researchAndDevelopment": "52635000",
            "operatingExpenses": "192935000",
            "investmentIncomeNet": "9567000",
            "netInterestIncome": "9567000",
            "interestIncome": "9567000",
            "interestExpense": "None",
            "nonInterestIncome": "201612000",
            "otherNonOperatingIncome": "-126000",
            "depreciation": "None",
            "depreciationAndAmortization": "4000000",
            "incomeBeforeTax": "-26889000",
            "incomeTaxExpense": "-594000",
            "interestAndDebtExpense": "None",
            "netIncomeFromContinuingOperations": "-26295000",
            "comprehensiveIncomeNetOfTax": "-26295000",
            "ebit": "-36330000",
            "ebitda": "-32330000",
            "netIncome": "-26295000"
        },
        {
            "fiscalDateEnding": "2023-09-30",
            "reportedCurrency": "USD",
            "grossProfit": "116982000",
            "totalRevenue": "175807000",
            "costOfRevenue": "339865000",
            "costofGoodsAndServicesSold": "58825000",
            "operatingIncome": "-302203000",
            "sellingGeneralAndAdministrative": "277730000",
            "researchAndDevelopment": "141455000",
            "operatingExpenses": "419185000",
            "investmentIncomeNet": "6183000",
            "netInterestIncome": "6183000",
            "interestIncome": "6183000",
            "interestExpense": "None",
            "nonInterestIncome": "175807000",
            "otherNonOperatingIncome": "-265000",
            "depreciation": "None",
            "depreciationAndAmortization": "3300000",
            "incomeBeforeTax": "-296285000",
            "incomeTaxExpense": "819000",
            "interestAndDebtExpense": "None",
            "netIncomeFromContinuingOperations": "-297104000",
            "comprehensiveIncomeNetOfTax": "-297104000",
            "ebit": "-302203000",
            "ebitda": "-298903000",
            "netIncome": "-297104000"
        },
        {
            "fiscalDateEnding": "2022-09-30",
            "reportedCurrency": "USD",
            "grossProfit": "86549000",
            "totalRevenue": "119168000",
            "costOfRevenue": "32619000",
            "costofGoodsAndServicesSold": "32619000",
            "operatingIncome": "-25663000",
            "sellingGeneralAndAdministrative": "20640000",
            "researchAndDevelopment": "30090000",
            "operatingExpenses": "112212000",
            "investmentIncomeNet": "None",
            "netInterestIncome": "1537000",
            "interestIncome": "1537000",
            "interestExpense": "None",
            "nonInterestIncome": "None",
            "otherNonOperatingIncome": "529000",
            "depreciation": "None",
            "depreciationAndAmortization": "2104000",
            "incomeBeforeTax": "-23597000",
            "incomeTaxExpense": "276000",
            "interestAndDebtExpense": "None",
            "netIncomeFromContinuingOperations": "-23873000",
            "comprehensiveIncomeNetOfTax": "-23873000",
            "ebit": "-25663000",
            "ebitda": "-23559000",
            "netIncome": "-23873000"
        }
    ]
}